syslogger/__init__.py
syslogger/syslogger.py
first_yup-1.0.0.4.dist-info/METADATA
first_yup-1.0.0.4.dist-info/WHEEL
first_yup-1.0.0.4.dist-info/top_level.txt
first_yup-1.0.0.4.dist-info/RECORD
