Metadata-Version: 2.1
Name: first-yup
Version: 1.0.0.4
Summary: First Package
Home-page: UNKNOWN
Author: syupoh
Author-email: syup5@snu.ac.kr
License: MIT
Platform: UNKNOWN
Requires-Python: >=3
